langchain_anthropic_smart_cache/__init__.py
langchain_anthropic_smart_cache/cache.py
langchain_anthropic_smart_cache/core.py
langchain_anthropic_smart_cache/utils.py
langchain_anthropic_smart_cache-0.2.3.dist-info/licenses/LICENSE
langchain_anthropic_smart_cache-0.2.3.dist-info/METADATA
langchain_anthropic_smart_cache-0.2.3.dist-info/WHEEL
langchain_anthropic_smart_cache-0.2.3.dist-info/top_level.txt
langchain_anthropic_smart_cache-0.2.3.dist-info/RECORD
