Metadata-Version: 2.4
Name: langchain-anthropic-smart-cache
Version: 0.2.3
Summary: Intelligent cache management for LangChain Anthropic models with advanced optimization strategies
Author-email: Imran Arshad <imran.arshad01@gmail.com>
License-Expression: MIT
Project-URL: Homepage, https://github.com/imranarshad/langchain-anthropic-smart-cache
Project-URL: Bug Reports, https://github.com/imranarshad/langchain-anthropic-smart-cache/issues
Project-URL: Source, https://github.com/imranarshad/langchain-anthropic-smart-cache
Project-URL: Documentation, https://github.com/imranarshad/langchain-anthropic-smart-cache#readme
Keywords: langchain,prompt cache,anthropic,claude,optimization,ai,llm
Classifier: Development Status :: 4 - Beta
Classifier: Intended Audience :: Developers
Classifier: Operating System :: OS Independent
Classifier: Programming Language :: Python :: 3
Classifier: Programming Language :: Python :: 3.8
Classifier: Programming Language :: Python :: 3.9
Classifier: Programming Language :: Python :: 3.10
Classifier: Programming Language :: Python :: 3.11
Classifier: Programming Language :: Python :: 3.12
Classifier: Topic :: Software Development :: Libraries :: Python Modules
Classifier: Topic :: Scientific/Engineering :: Artificial Intelligence
Requires-Python: >=3.8
License-File: LICENSE
Requires-Dist: langchain-core>=0.1.0
Requires-Dist: tiktoken>=0.5.0
Provides-Extra: dev
Requires-Dist: pytest>=6.0; extra == "dev"
Requires-Dist: pytest-cov>=2.0; extra == "dev"
Requires-Dist: black>=22.0; extra == "dev"
Requires-Dist: flake8>=4.0; extra == "dev"
Requires-Dist: mypy>=0.950; extra == "dev"
Requires-Dist: build>=0.10.0; extra == "dev"
Requires-Dist: twine>=4.0.0; extra == "dev"
Provides-Extra: anthropic
Requires-Dist: langchain-anthropic>=0.1.0; extra == "anthropic"
Dynamic: license-file
